tf_slim/__init__.py
tf_slim/evaluation.py
tf_slim/evaluation_test.py
tf_slim/learning.py
tf_slim/learning_test.py
tf_slim/model_analyzer.py
tf_slim/queues.py
tf_slim/summaries.py
tf_slim/summaries_test.py
tf_slim/data/__init__.py
tf_slim/data/data_decoder.py
tf_slim/data/data_provider.py
tf_slim/data/dataset.py
tf_slim/data/dataset_data_provider.py
tf_slim/data/dataset_data_provider_test.py
tf_slim/data/parallel_reader.py
tf_slim/data/parallel_reader_test.py
tf_slim/data/prefetch_queue.py
tf_slim/data/prefetch_queue_test.py
tf_slim/data/test_utils.py
tf_slim/data/tfexample_decoder.py
tf_slim/data/tfexample_decoder_test.py
tf_slim/nets/__init__.py
tf_slim/nets/alexnet.py
tf_slim/nets/alexnet_test.py
tf_slim/nets/inception.py
tf_slim/nets/inception_v1.py
tf_slim/nets/inception_v1_test.py
tf_slim/nets/inception_v2.py
tf_slim/nets/inception_v2_test.py
tf_slim/nets/inception_v3.py
tf_slim/nets/inception_v3_test.py
tf_slim/nets/overfeat.py
tf_slim/nets/overfeat_test.py
tf_slim/nets/resnet_utils.py
tf_slim/nets/resnet_v1.py
tf_slim/nets/resnet_v1_test.py
tf_slim/nets/resnet_v2.py
tf_slim/nets/resnet_v2_test.py
tf_slim/nets/vgg.py
tf_slim/nets/vgg_test.py
tf_slim-1.0.dist-info/LICENSE
tf_slim-1.0.dist-info/METADATA
tf_slim-1.0.dist-info/WHEEL
tf_slim-1.0.dist-info/top_level.txt
tf_slim-1.0.dist-info/RECORD
