Metadata-Version: 2.1
Name: tf-slim
Version: 1.0
Summary: TF-Slim: A framework for flexible Reinforcement Learning research
Home-page: https://github.com/google-research/tf-slim
Author: The TF-Slim Team
Author-email: UNKNOWN
License: Apache 2.0
Project-URL: Source, https://github.com/google-research/tf-slim
Project-URL: Documentation, https://github.com/google-research/tf-slim
Project-URL: Bug Reports, https://github.com/google-research/tf-slim/issues
Keywords: tensorflow tf-slim python machine learning
Platform: UNKNOWN
Classifier: Development Status :: 4 - Beta
Classifier: Intended Audience :: Developers
Classifier: Intended Audience :: Education
Classifier: Intended Audience :: Science/Research
Classifier: License :: OSI Approved :: Apache Software License
Classifier: Programming Language :: Python :: 2
Classifier: Programming Language :: Python :: 2.7
Classifier: Programming Language :: Python :: 3
Classifier: Programming Language :: Python :: 3.4
Classifier: Programming Language :: Python :: 3.5
Classifier: Programming Language :: Python :: 3.6
Classifier: Topic :: Scientific/Engineering
Classifier: Topic :: Scientific/Engineering :: Mathematics
Classifier: Topic :: Scientific/Engineering :: Artificial Intelligence
Classifier: Topic :: Software Development
Classifier: Topic :: Software Development :: Libraries
Classifier: Topic :: Software Development :: Libraries :: Python Modules
Requires-Dist: absl-py (>=0.2.2)
